exam_json_generator/__init__.py
exam_json_generator/__main__.py
exam_json_generator/extractor.py
exam_json_generator-1.0.4.dist-info/LICENSE
exam_json_generator-1.0.4.dist-info/METADATA
exam_json_generator-1.0.4.dist-info/WHEEL
exam_json_generator-1.0.4.dist-info/entry_points.txt
exam_json_generator-1.0.4.dist-info/RECORD
