Metadata-Version: 2.3
Name: exam_json_generator
Version: 1.0.4
Summary: 
License: GLP-3
Author: jrubioh
Author-email: jrubio@guardiacivil.es
Requires-Python: >=3.13
Classifier: License :: Other/Proprietary License
Classifier: Programming Language :: Python :: 3
Classifier: Programming Language :: Python :: 3.13
Requires-Dist: python-docx (>=1.1.2,<2.0.0)
Requires-Dist: termcolor (>=3.1.0,<4.0.0)
